<?xml version="1.0" encoding="UTF-8"?>
<persistence version="2.1" xmlns="http://xmlns.jcp.org/xml/ns/persistence" xmlns:xsi="http://www.w3.org/2001/XMLSchema-instance" xsi:schemaLocation="http://xmlns.jcp.org/xml/ns/persistence http://xmlns.jcp.org/xml/ns/persistence/persistence_2_1.xsd">
	<persistence-unit name="TallerPruebasDanielGalvis">
		<class>co.edu.icesi.miniproyecto.model.Tmio1Bus</class>
		<class>co.edu.icesi.miniproyecto.model.Tmio1Conductore</class>
		<class>co.edu.icesi.miniproyecto.model.Tmio1Ruta</class>
		<class>co.edu.icesi.miniproyecto.model.Tmio1Servicio</class>
		<class>co.edu.icesi.miniproyecto.model.Tmio1ServicioPK</class>
		<class>co.edu.icesi.miniproyecto.model.Tmio1ServiciosSitio</class>
		<class>co.edu.icesi.miniproyecto.model.Tmio1ServiciosSitioPK</class>
		<class>co.edu.icesi.miniproyecto.model.Tmio1Sitio</class>
		<class>co.edu.icesi.miniproyecto.model.Tmio1SitiosRuta</class>
		<class>co.edu.icesi.miniproyecto.model.Tmio1Usuario</class>
		<class>co.edu.icesi.miniproyecto.model.Tmio1SitiosRutaPK</class>
	</persistence-unit>
</persistence>
